elephas/__init__.py
elephas/ml_model.py
elephas/spark_model.py
elephas/worker.py
elephas/enums/__init__.py
elephas/enums/frequency.py
elephas/enums/modes.py
elephas/ml/__init__.py
elephas/ml/adapter.py
elephas/ml/params.py
elephas/mllib/__init__.py
elephas/mllib/adapter.py
elephas/parameter/__init__.py
elephas/parameter/client.py
elephas/parameter/factory.py
elephas/parameter/server.py
elephas/utils/__init__.py
elephas/utils/functional_utils.py
elephas/utils/model_utils.py
elephas/utils/notebook_utils.py
elephas/utils/rdd_utils.py
elephas/utils/rwlock.py
elephas/utils/serialization.py
elephas/utils/sockets.py
elephas/utils/versioning_utils.py
elephas-7.2.0.dist-info/METADATA
elephas-7.2.0.dist-info/WHEEL
elephas-7.2.0.dist-info/licenses/LICENSE
elephas-7.2.0.dist-info/RECORD
