Metadata-Version: 2.4
Name: elephas
Version: 7.2.0
Summary: Distributed deep learning on Spark with Keras
Project-URL: Homepage, https://danielenricocahall.github.io/elephas/
Author-email: Daniel Cahall <danielenricocahall@gmail.com>
License: MIT
License-File: LICENSE
Requires-Python: <3.13,>=3.9
Requires-Dist: cython==0.29.33
Requires-Dist: flask==2.3.3
Requires-Dist: h5py==3.11.0
Requires-Dist: numpy<2.0.0
Requires-Dist: pyspark<=4.0.0
Requires-Dist: tensorflow<2.20,>2.2
